monitrix/__init__.py
monitrix/command/cil.py
monitrix/core/main_screen.py
monitrix/core/mask.py
monitrix/core/plane_geometry.py
monitrix/core/results.py
monitrix/model/dnyolocr.py
monitrix/model/training/train.py
monitrix/model/weights/yolo11n_seg_c300.pt
monitrix/ocr/number.py
monitrix/utils/logger.py
monitrix/utils/plotting.py
monitrix/utils/video.py
monitrix-0.0.3.dev0.dist-info/LICENSE
monitrix-0.0.3.dev0.dist-info/METADATA
monitrix-0.0.3.dev0.dist-info/WHEEL
monitrix-0.0.3.dev0.dist-info/entry_points.txt
monitrix-0.0.3.dev0.dist-info/top_level.txt
monitrix-0.0.3.dev0.dist-info/RECORD
