Metadata-Version: 2.1
Name: monitrix
Version: 0.0.3.dev0
Summary: An advanced monitoring tool with OCR and image recognition capabilities
Author-email: Arisaka Naoya <arisakanaoya@gmail.com>
License: GNU Affero General Public License v3 or later (AGPLv3+)
Project-URL: Homepage, https://github.com/arsklab/monitrix
Project-URL: Source, https://github.com/arsklab/monitrix
Project-URL: Issues, https://github.com/arsklab/monitrix/issues
Keywords: monitoring,ocr,computer-vision,yolo,image-recognition
Classifier: Programming Language :: Python :: 3
Classifier: Programming Language :: Python :: 3.10
Classifier: Programming Language :: Python :: 3.11
Classifier: License :: OSI Approved :: GNU Affero General Public License v3 or later (AGPLv3+)
Classifier: Development Status :: 4 - Beta
Classifier: Operating System :: OS Independent
Classifier: Topic :: Scientific/Engineering :: Image Recognition
Classifier: Topic :: Scientific/Engineering :: Artificial Intelligence
Classifier: Topic :: Software Development :: Libraries :: Python Modules
Classifier: Intended Audience :: Science/Research
Classifier: Intended Audience :: Developers
Classifier: Environment :: Console
Classifier: Natural Language :: English
Classifier: Natural Language :: Japanese
Requires-Python: >=3.10
License-File: LICENSE
Requires-Dist: ultralytics>=8.3.0
Requires-Dist: easyocr>=1.7.0
Requires-Dist: opencv-python>=4.5.0
Requires-Dist: numpy>=1.25.0
Requires-Dist: tqdm>=4.65.0
